{ "time": "2016-02-20 21:51:24.1092", "level": "DEBUG", "message": "hello from Admin:TestAction" }
{ "time": "2016-02-20 21:51:26.9039", "level": "ERROR", "message": "test" }
{ "time": "2016-02-20 23:42:17.5380", "level": "ERROR", "message": "The IControllerFactory 'ACTS.UI.Infrastructure.NinjectControllerFactory' did not return a controller for the name 'test'." }
{ "time": "2016-02-20 23:42:37.6517", "level": "DEBUG", "message": "hello from Admin:TestAction" }
{ "time": "2016-02-20 23:42:43.5531", "level": "ERROR", "message": "test" }
{ "time": "2016-02-20 23:42:43.5976", "level": "ERROR", "message": "test" }
{ "time": "2016-02-20 23:44:43.6697", "level": "DEBUG", "message": "hello from Admin:TestAction" }
{ "time": "2016-02-20 23:44:50.7225", "level": "ERROR", "message": "test" }
{ "time": "2016-02-20 23:44:50.7225", "level": "ERROR", "message": "test" }
{ "time": "2016-02-20 23:45:12.3214", "level": "ERROR", "message": "The IControllerFactory 'ACTS.UI.Infrastructure.NinjectControllerFactory' did not return a controller for the name 'fds'." }
{ "time": "2016-02-21 01:09:10.1612", "level": "INFO", "message": "MVC Application launched." }
{ "time": "2016-02-21 01:09:10.1842", "level": "TRACE", "message": "MVC Application start configuring." }
{ "time": "2016-02-21 01:09:11.7968", "level": "TRACE", "message": "MVC Application end configuring." }
{ "time": "2016-02-21 01:09:12.4412", "level": "TRACE", "message": "Owin start configuring." }
{ "time": "2016-02-21 01:09:12.4772", "level": "TRACE", "message": "Owin end configuring." }
{ "time": "2016-02-21 01:09:13.2757", "level": "INFO", "message": "MVC Application launched." }
{ "time": "2016-02-21 01:13:34.4536", "level": "INFO", "message": "MVC Application launched." }
{ "time": "2016-02-21 01:13:34.8323", "level": "TRACE", "message": "MVC Application start configuring." }
{ "time": "2016-02-21 01:13:35.9459", "level": "TRACE", "message": "MVC Application end configuring." }
{ "time": "2016-02-21 01:13:37.4286", "level": "TRACE", "message": "Owin start configuring." }
{ "time": "2016-02-21 01:13:37.4716", "level": "TRACE", "message": "Owin end configuring." }
{ "time": "2016-02-21 01:13:38.3305", "level": "INFO", "message": "MVC Application launched." }
{ "time": "2016-02-21 02:19:23.3445", "level": "DEBUG", "message": "MVC Application initialized." }
{ "time": "2016-02-21 02:19:23.3726", "level": "TRACE", "message": "MVC Application start configuring." }
{ "time": "2016-02-21 02:19:26.2434", "level": "TRACE", "message": "MVC Application end configuring." }
{ "time": "2016-02-21 02:19:26.8672", "level": "TRACE", "message": "Owin start configuring." }
{ "time": "2016-02-21 02:19:26.8932", "level": "TRACE", "message": "Owin end configuring." }
{ "time": "2016-02-21 02:19:32.2479", "level": "ERROR", "message": "Error loading Ninject component ICache\r\nNo such component has been registered in the kernel's component container.\r\n\r\nSuggestions:\r\n  1) If you have created a custom subclass for KernelBase, ensure that you have properly\r\n     implemented the AddComponents() method.\r\n  2) Ensure that you have not removed the component from the container via a call to RemoveAll().\r\n  3) Ensure you have not accidentally created more than one kernel.\r\n" }
{ "time": "2016-02-21 02:22:19.5747", "level": "ERROR", "message": "Error loading Ninject component ICache\r\nNo such component has been registered in the kernel's component container.\r\n\r\nSuggestions:\r\n  1) If you have created a custom subclass for KernelBase, ensure that you have properly\r\n     implemented the AddComponents() method.\r\n  2) Ensure that you have not removed the component from the container via a call to RemoveAll().\r\n  3) Ensure you have not accidentally created more than one kernel.\r\n" }
{ "time": "2016-02-21 02:23:25.6746", "level": "ERROR", "message": "Error loading Ninject component ICache\r\nNo such component has been registered in the kernel's component container.\r\n\r\nSuggestions:\r\n  1) If you have created a custom subclass for KernelBase, ensure that you have properly\r\n     implemented the AddComponents() method.\r\n  2) Ensure that you have not removed the component from the container via a call to RemoveAll().\r\n  3) Ensure you have not accidentally created more than one kernel.\r\n" }
{ "time": "2016-02-21 02:23:50.4381", "level": "ERROR", "message": "Error loading Ninject component ICache\r\nNo such component has been registered in the kernel's component container.\r\n\r\nSuggestions:\r\n  1) If you have created a custom subclass for KernelBase, ensure that you have properly\r\n     implemented the AddComponents() method.\r\n  2) Ensure that you have not removed the component from the container via a call to RemoveAll().\r\n  3) Ensure you have not accidentally created more than one kernel.\r\n" }
{ "time": "2016-02-21 02:24:16.6517", "level": "ERROR", "message": "Error loading Ninject component ICache\r\nNo such component has been registered in the kernel's component container.\r\n\r\nSuggestions:\r\n  1) If you have created a custom subclass for KernelBase, ensure that you have properly\r\n     implemented the AddComponents() method.\r\n  2) Ensure that you have not removed the component from the container via a call to RemoveAll().\r\n  3) Ensure you have not accidentally created more than one kernel.\r\n" }
{ "time": "2016-02-21 02:26:30.4906", "level": "DEBUG", "message": "MVC Application initialized." }
{ "time": "2016-02-21 02:26:30.5121", "level": "TRACE", "message": "MVC Application start configuring." }
{ "time": "2016-02-21 02:26:32.2424", "level": "TRACE", "message": "MVC Application end configuring." }
{ "time": "2016-02-21 02:26:33.0472", "level": "TRACE", "message": "Owin start configuring." }
{ "time": "2016-02-21 02:26:33.0752", "level": "TRACE", "message": "Owin end configuring." }
{ "time": "2016-02-21 02:27:22.6354", "level": "ERROR", "message": "Object reference not set to an instance of an object." }
{ "time": "2016-02-21 02:28:24.5080", "level": "DEBUG", "message": "MVC Application initialized." }
{ "time": "2016-02-21 02:28:24.5350", "level": "TRACE", "message": "MVC Application start configuring." }
{ "time": "2016-02-21 02:28:26.2961", "level": "TRACE", "message": "MVC Application end configuring." }
{ "time": "2016-02-21 02:28:27.0352", "level": "TRACE", "message": "Owin start configuring." }
{ "time": "2016-02-21 02:28:27.0523", "level": "TRACE", "message": "Owin end configuring." }
{ "time": "2016-02-21 02:30:26.2720", "level": "ERROR", "message": "Object reference not set to an instance of an object." }
{ "time": "2016-02-21 02:36:13.3615", "level": "DEBUG", "message": "MVC Application initialized." }
{ "time": "2016-02-21 02:36:13.3895", "level": "TRACE", "message": "MVC Application start configuring." }
{ "time": "2016-02-21 02:39:09.4539", "level": "DEBUG", "message": "MVC Application initialized." }
{ "time": "2016-02-21 02:39:09.7087", "level": "TRACE", "message": "MVC Application start configuring." }
{ "time": "2016-02-21 02:39:10.9701", "level": "TRACE", "message": "MVC Application end configuring." }
{ "time": "2016-02-21 02:39:12.1449", "level": "TRACE", "message": "Owin start configuring." }
{ "time": "2016-02-21 02:39:12.1929", "level": "TRACE", "message": "Owin end configuring." }
{ "time": "2016-02-21 02:39:13.5768", "level": "TRACE", "message": "Executing action Home.Index" }
{ "time": "2016-02-21 02:39:13.6078", "level": "TRACE", "message": "Executed action Home.Index" }
{ "time": "2016-02-21 02:39:19.1776", "level": "TRACE", "message": "Executing action Account.AuthenticationLink" }
{ "time": "2016-02-21 02:39:19.1776", "level": "TRACE", "message": "Executed action Account.AuthenticationLink" }
{ "time": "2016-02-21 02:40:16.7921", "level": "TRACE", "message": "Executing action Admin.Dashboard" }
{ "time": "2016-02-21 02:40:16.7971", "level": "TRACE", "message": "Executed action Admin.Dashboard" }
{ "time": "2016-02-21 02:40:29.0762", "level": "TRACE", "message": "Executing action Admin.test" }
{ "time": "2016-02-21 02:40:29.0762", "level": "DEBUG", "message": "hello from Admin:TestAction" }
{ "time": "2016-02-21 02:40:36.6391", "level": "TRACE", "message": "Executed action Admin.test" }
{ "time": "2016-02-21 02:40:36.6591", "level": "ERROR", "message": "test" }
{ "time": "2016-02-21 02:47:28.2516", "level": "DEBUG", "message": "MVC Application initialized." }
{ "time": "2016-02-21 02:47:28.2826", "level": "TRACE", "message": "MVC Application start configuring." }
{ "time": "2016-02-21 02:47:30.4887", "level": "TRACE", "message": "MVC Application end configuring." }
{ "time": "2016-02-21 02:47:30.9554", "level": "TRACE", "message": "Owin start configuring." }
{ "time": "2016-02-21 02:47:30.9694", "level": "TRACE", "message": "Owin end configuring." }
{ "time": "2016-02-21 02:47:33.2072", "level": "TRACE", "message": "Start executing action test from AdminController" }
{ "time": "2016-02-21 02:47:33.2072", "level": "DEBUG", "message": "hello from Admin:TestAction" }
{ "time": "2016-02-21 02:47:33.2202", "level": "ERROR", "message": "test" }
{ "time": "2016-02-21 02:56:05.1680", "level": "TRACE", "message": "Start executing action test from AdminController" }
{ "time": "2016-02-21 02:56:05.1680", "level": "DEBUG", "message": "hello from Admin:TestAction" }
{ "time": "2016-02-21 02:56:05.1680", "level": "ERROR", "message": "test" }
{ "time": "2016-02-21 02:56:20.0969", "level": "TRACE", "message": "Start executing action Dashboard from AdminController" }
{ "time": "2016-02-21 02:56:20.0969", "level": "TRACE", "message": "Executed action Admin.Dashboard" }
{ "time": "2016-02-21 22:45:39.1033", "level": "DEBUG", "message": "MVC Application initialized." }
{ "time": "2016-02-21 22:45:39.3055", "level": "TRACE", "message": "MVC Application start configuring." }
{ "time": "2016-02-21 22:45:52.2247", "level": "TRACE", "message": "MVC Application end configuring." }
{ "time": "2016-02-21 22:45:54.1408", "level": "TRACE", "message": "Owin start configuring." }
{ "time": "2016-02-21 22:45:54.1789", "level": "TRACE", "message": "Owin end configuring." }
{ "time": "2016-02-21 22:45:57.4515", "level": "TRACE", "message": "Start executing action Login from AccountController" }
{ "time": "2016-02-21 22:45:57.7600", "level": "TRACE", "message": "Executed action Login from AccountController" }
{ "time": "2016-02-21 22:46:15.1790", "level": "TRACE", "message": "Start executing action Login from AccountController" }
{ "time": "2016-02-21 22:46:17.6564", "level": "TRACE", "message": "User admin is logged in." }
{ "time": "2016-02-21 22:46:17.7309", "level": "TRACE", "message": "Executed action Login from AccountController" }
{ "time": "2016-02-21 22:46:17.8905", "level": "TRACE", "message": "Start executing action Logging from LoggingController" }
{ "time": "2016-02-21 22:46:17.8945", "level": "ERROR", "message": "The parameters dictionary contains a null entry for parameter 'nomDays' of non-nullable type 'System.Double' for method 'System.Web.Mvc.ActionResult LogsForNDays(Double)' in 'ACTS.UI.Areas.Admin.Controllers.LoggingController'. An optional parameter must be a reference type, a nullable type, or be declared as an optional parameter.\r\nParameter name: parameters" }
{ "time": "2016-02-21 22:46:23.4472", "level": "TRACE", "message": "Start executing action Index from LoggingController" }
{ "time": "2016-02-21 22:46:23.4953", "level": "TRACE", "message": "Executed action Index from LoggingController" }
{ "time": "2016-02-21 22:46:27.0169", "level": "ERROR", "message": "E:\\study\\ACTS\\ACTS.UI\\Areas\\Admin\\Views\\Logging\\Logging.cshtml(43): error CS1061: 'LogEntry' does not contain a definition for 'EmployeeId' and no extension method 'EmployeeId' accepting a first argument of type 'LogEntry' could be found (are you missing a using directive or an assembly reference?)" }
{ "time": "2016-02-21 22:46:31.5521", "level": "TRACE", "message": "Start executing action Dashboard from AdminController" }
{ "time": "2016-02-21 22:46:31.5521", "level": "TRACE", "message": "Executed action Dashboard from AdminController" }
{ "time": "2016-02-21 23:54:23.4545", "level": "DEBUG", "message": "MVC Application initialized." }
{ "time": "2016-02-21 23:54:23.4950", "level": "TRACE", "message": "MVC Application start configuring." }
{ "time": "2016-02-21 23:54:25.9239", "level": "TRACE", "message": "MVC Application end configuring." }
{ "time": "2016-02-21 23:54:26.6463", "level": "TRACE", "message": "Owin start configuring." }
{ "time": "2016-02-21 23:54:26.6633", "level": "TRACE", "message": "Owin end configuring." }
{ "time": "2016-02-21 23:54:26.9721", "level": "TRACE", "message": "Start executing action Index from HomeController" }
{ "time": "2016-02-21 23:54:26.9976", "level": "TRACE", "message": "Executed action Index from HomeController" }
{ "time": "2016-02-21 23:54:29.3452", "level": "TRACE", "message": "Start executing action AuthenticationLink from AccountController" }
{ "time": "2016-02-21 23:54:29.3452", "level": "TRACE", "message": "Executed action AuthenticationLink from AccountController" }
{ "time": "2016-02-21 23:57:19.6519", "level": "DEBUG", "message": "MVC Application initialized." }
{ "time": "2016-02-21 23:57:19.6699", "level": "TRACE", "message": "MVC Application start configuring." }
{ "time": "2016-02-21 23:57:21.6610", "level": "TRACE", "message": "MVC Application end configuring." }
{ "time": "2016-02-21 23:57:22.3495", "level": "TRACE", "message": "Owin start configuring." }
{ "time": "2016-02-21 23:57:22.3656", "level": "TRACE", "message": "Owin end configuring." }
{ "time": "2016-02-21 23:57:22.6063", "level": "TRACE", "message": "Start executing action Index from HomeController" }
{ "time": "2016-02-21 23:57:22.6273", "level": "TRACE", "message": "Executed action Index from HomeController" }
{ "time": "2016-02-21 23:57:24.5156", "level": "TRACE", "message": "Start executing action AuthenticationLink from AccountController" }
{ "time": "2016-02-21 23:57:24.5156", "level": "TRACE", "message": "Executed action AuthenticationLink from AccountController" }
{ "time": "2016-02-22 00:30:33.5174", "level": "TRACE", "message": "Start executing action Login from AccountController" }
{ "time": "2016-02-22 00:30:33.5174", "level": "TRACE", "message": "Executed action Login from AccountController" }
{ "time": "2016-02-22 00:30:40.1670", "level": "TRACE", "message": "Start executing action Login from AccountController" }
{ "time": "2016-02-22 00:30:42.3987", "level": "TRACE", "message": "User admin is logged in." }
{ "time": "2016-02-22 00:30:42.3987", "level": "TRACE", "message": "Executed action Login from AccountController" }
{ "time": "2016-02-22 00:30:42.4532", "level": "TRACE", "message": "Start executing action Dashboard from AdminController" }
{ "time": "2016-02-22 00:30:42.4532", "level": "TRACE", "message": "Executed action Dashboard from AdminController" }
{ "time": "2016-02-22 00:30:51.3631", "level": "ERROR", "message": "The IControllerFactory 'ACTS.UI.Infrastructure.NinjectControllerFactory' did not return a controller for the name 'Log'." }
{ "time": "2016-02-22 00:37:23.5228", "level": "DEBUG", "message": "MVC Application initialized." }
{ "time": "2016-02-22 00:37:23.5884", "level": "TRACE", "message": "MVC Application start configuring." }
{ "time": "2016-02-22 00:37:27.2403", "level": "TRACE", "message": "MVC Application end configuring." }
{ "time": "2016-02-22 00:37:27.9443", "level": "TRACE", "message": "Owin start configuring." }
{ "time": "2016-02-22 00:37:27.9623", "level": "TRACE", "message": "Owin end configuring." }
{ "time": "2016-02-22 00:37:28.3501", "level": "TRACE", "message": "Start executing action Index from HomeController" }
{ "time": "2016-02-22 00:37:28.3721", "level": "TRACE", "message": "Executed action Index from HomeController" }
{ "time": "2016-02-22 00:37:30.5796", "level": "TRACE", "message": "Start executing action AuthenticationLink from AccountController" }
{ "time": "2016-02-22 00:37:30.5796", "level": "TRACE", "message": "Executed action AuthenticationLink from AccountController" }
{ "time": "2016-02-22 00:37:34.9547", "level": "TRACE", "message": "Start executing action Index from LogController" }
{ "time": "2016-02-22 00:37:36.0284", "level": "TRACE", "message": "Executed action Index from LogController" }
{ "time": "2016-02-22 00:37:36.0344", "level": "ERROR", "message": "The view 'Logging' or its master was not found or no view engine supports the searched locations. The following locations were searched:\r\n~\/Areas\/Admin\/Views\/Log\/Logging.aspx\r\n~\/Areas\/Admin\/Views\/Log\/Logging.ascx\r\n~\/Areas\/Admin\/Views\/Shared\/Logging.aspx\r\n~\/Areas\/Admin\/Views\/Shared\/Logging.ascx\r\n~\/Views\/Log\/Logging.aspx\r\n~\/Views\/Log\/Logging.ascx\r\n~\/Views\/Shared\/Logging.aspx\r\n~\/Views\/Shared\/Logging.ascx\r\n~\/Areas\/Admin\/Views\/Log\/Logging.cshtml\r\n~\/Areas\/Admin\/Views\/Log\/Logging.vbhtml\r\n~\/Areas\/Admin\/Views\/Shared\/Logging.cshtml\r\n~\/Areas\/Admin\/Views\/Shared\/Logging.vbhtml\r\n~\/Views\/Log\/Logging.cshtml\r\n~\/Views\/Log\/Logging.vbhtml\r\n~\/Views\/Shared\/Logging.cshtml\r\n~\/Views\/Shared\/Logging.vbhtml" }
{ "time": "2016-02-22 00:37:42.5241", "level": "TRACE", "message": "Start executing action Dashboard from AdminController" }
{ "time": "2016-02-22 00:37:42.5241", "level": "TRACE", "message": "Executed action Dashboard from AdminController" }
{ "time": "2016-02-22 00:37:54.2970", "level": "TRACE", "message": "Start executing action Index from MyAccountController" }
{ "time": "2016-02-22 00:37:54.5775", "level": "TRACE", "message": "Executed action Index from MyAccountController" }
{ "time": "2016-02-22 00:37:58.5792", "level": "TRACE", "message": "Start executing action Index from LogController" }
{ "time": "2016-02-22 00:37:58.5792", "level": "TRACE", "message": "Executed action Index from LogController" }
{ "time": "2016-02-22 00:37:58.5792", "level": "ERROR", "message": "The view 'Logging' or its master was not found or no view engine supports the searched locations. The following locations were searched:\r\n~\/Areas\/Admin\/Views\/Log\/Logging.aspx\r\n~\/Areas\/Admin\/Views\/Log\/Logging.ascx\r\n~\/Areas\/Admin\/Views\/Shared\/Logging.aspx\r\n~\/Areas\/Admin\/Views\/Shared\/Logging.ascx\r\n~\/Views\/Log\/Logging.aspx\r\n~\/Views\/Log\/Logging.ascx\r\n~\/Views\/Shared\/Logging.aspx\r\n~\/Views\/Shared\/Logging.ascx\r\n~\/Areas\/Admin\/Views\/Log\/Logging.cshtml\r\n~\/Areas\/Admin\/Views\/Log\/Logging.vbhtml\r\n~\/Areas\/Admin\/Views\/Shared\/Logging.cshtml\r\n~\/Areas\/Admin\/Views\/Shared\/Logging.vbhtml\r\n~\/Views\/Log\/Logging.cshtml\r\n~\/Views\/Log\/Logging.vbhtml\r\n~\/Views\/Shared\/Logging.cshtml\r\n~\/Views\/Shared\/Logging.vbhtml" }
{ "time": "2016-02-22 00:39:18.6450", "level": "DEBUG", "message": "MVC Application initialized." }
{ "time": "2016-02-22 00:39:18.7241", "level": "TRACE", "message": "MVC Application start configuring." }
{ "time": "2016-02-22 00:39:19.9910", "level": "TRACE", "message": "MVC Application end configuring." }
{ "time": "2016-02-22 00:39:20.5048", "level": "TRACE", "message": "Owin start configuring." }
{ "time": "2016-02-22 00:39:20.5288", "level": "TRACE", "message": "Owin end configuring." }
{ "time": "2016-02-22 00:39:23.2741", "level": "TRACE", "message": "Start executing action Index from LogController" }
{ "time": "2016-02-22 00:39:23.2991", "level": "TRACE", "message": "Executed action Index from LogController" }
{ "time": "2016-02-22 00:39:26.8971", "level": "ERROR", "message": "DbArithmeticExpression arguments must have a numeric common type." }
{ "time": "2016-02-22 00:41:00.5008", "level": "DEBUG", "message": "MVC Application initialized." }
{ "time": "2016-02-22 00:41:00.5258", "level": "TRACE", "message": "MVC Application start configuring." }
{ "time": "2016-02-22 00:41:02.9777", "level": "TRACE", "message": "MVC Application end configuring." }
{ "time": "2016-02-22 00:41:03.6896", "level": "TRACE", "message": "Owin start configuring." }
{ "time": "2016-02-22 00:41:03.7166", "level": "TRACE", "message": "Owin end configuring." }
{ "time": "2016-02-22 00:41:04.0249", "level": "TRACE", "message": "Start executing action Index from HomeController" }
{ "time": "2016-02-22 00:41:04.0449", "level": "TRACE", "message": "Executed action Index from HomeController" }
{ "time": "2016-02-22 00:41:05.6783", "level": "TRACE", "message": "Start executing action Index from LogController" }
{ "time": "2016-02-22 00:41:06.0005", "level": "TRACE", "message": "Start executing action AuthenticationLink from AccountController" }
{ "time": "2016-02-22 00:41:06.0005", "level": "TRACE", "message": "Executed action AuthenticationLink from AccountController" }
{ "time": "2016-02-22 00:41:53.3262", "level": "TRACE", "message": "Executed action Index from LogController" }
{ "time": "2016-02-22 00:41:57.6702", "level": "ERROR", "message": "DbArithmeticExpression arguments must have a numeric common type." }
{ "time": "2016-02-22 00:42:23.8780", "level": "TRACE", "message": "Start executing action Index from HomeController" }
{ "time": "2016-02-22 00:42:23.8780", "level": "TRACE", "message": "Executed action Index from HomeController" }
{ "time": "2016-02-22 00:42:23.8945", "level": "TRACE", "message": "Start executing action AuthenticationLink from AccountController" }
{ "time": "2016-02-22 00:42:23.8945", "level": "TRACE", "message": "Executed action AuthenticationLink from AccountController" }
{ "time": "2016-02-22 00:43:54.8634", "level": "DEBUG", "message": "MVC Application initialized." }
{ "time": "2016-02-22 00:43:54.8885", "level": "TRACE", "message": "MVC Application start configuring." }
{ "time": "2016-02-22 00:43:56.8990", "level": "TRACE", "message": "MVC Application end configuring." }
{ "time": "2016-02-22 00:43:57.5572", "level": "TRACE", "message": "Owin start configuring." }
{ "time": "2016-02-22 00:43:57.5982", "level": "TRACE", "message": "Owin end configuring." }
{ "time": "2016-02-22 00:43:57.9525", "level": "TRACE", "message": "Start executing action Index from HomeController" }
{ "time": "2016-02-22 00:43:57.9525", "level": "TRACE", "message": "Start executing action Index from LogController" }
{ "time": "2016-02-22 00:43:57.9775", "level": "TRACE", "message": "Executed action Index from HomeController" }
{ "time": "2016-02-22 00:44:00.3201", "level": "TRACE", "message": "Start executing action AuthenticationLink from AccountController" }
{ "time": "2016-02-22 00:44:00.3341", "level": "TRACE", "message": "Executed action AuthenticationLink from AccountController" }
{ "time": "2016-02-22 00:44:25.1298", "level": "TRACE", "message": "Executed action Index from LogController" }
{ "time": "2016-02-22 00:46:08.9989", "level": "ERROR", "message": "DbArithmeticExpression arguments must have a numeric common type." }
{ "time": "2016-02-22 00:58:47.1903", "level": "DEBUG", "message": "MVC Application initialized." }
{ "time": "2016-02-22 00:58:47.2053", "level": "TRACE", "message": "MVC Application start configuring." }
{ "time": "2016-02-22 00:58:49.9871", "level": "TRACE", "message": "MVC Application end configuring." }
{ "time": "2016-02-22 00:58:50.8798", "level": "TRACE", "message": "Owin start configuring." }
{ "time": "2016-02-22 00:58:50.9029", "level": "TRACE", "message": "Owin end configuring." }
{ "time": "2016-02-22 00:58:55.0715", "level": "TRACE", "message": "Start executing action Index from HomeController" }
{ "time": "2016-02-22 00:58:55.0925", "level": "TRACE", "message": "Executed action Index from HomeController" }
{ "time": "2016-02-22 00:58:56.8375", "level": "TRACE", "message": "Start executing action AuthenticationLink from AccountController" }
{ "time": "2016-02-22 00:58:56.8475", "level": "TRACE", "message": "Executed action AuthenticationLink from AccountController" }
{ "time": "2016-02-22 00:59:05.2111", "level": "TRACE", "message": "Start executing action Index from LogController" }
{ "time": "2016-02-22 00:59:08.1418", "level": "TRACE", "message": "Executed action Index from LogController" }
{ "time": "2016-02-22 00:59:25.1717", "level": "TRACE", "message": "Start executing action SetCulture from HomeController" }
{ "time": "2016-02-22 00:59:25.1747", "level": "TRACE", "message": "Executed action SetCulture from HomeController" }
{ "time": "2016-02-22 00:59:25.2308", "level": "TRACE", "message": "Start executing action Index from LogController" }
{ "time": "2016-02-22 00:59:29.8019", "level": "TRACE", "message": "Executed action Index from LogController" }
{ "time": "2016-02-22 01:05:31.4252", "level": "TRACE", "message": "Start executing action Index from LogController" }
{ "time": "2016-02-22 01:05:31.4252", "level": "TRACE", "message": "Executed action Index from LogController" }
{ "time": "2016-02-22 01:12:13.8459", "level": "DEBUG", "message": "MVC Application initialized." }
{ "time": "2016-02-22 01:12:13.9120", "level": "TRACE", "message": "MVC Application start configuring." }
{ "time": "2016-02-22 01:12:15.1347", "level": "TRACE", "message": "MVC Application end configuring." }
{ "time": "2016-02-22 01:12:15.6621", "level": "TRACE", "message": "Owin start configuring." }
{ "time": "2016-02-22 01:12:15.6852", "level": "TRACE", "message": "Owin end configuring." }
{ "time": "2016-02-22 01:12:16.3226", "level": "TRACE", "message": "Start executing action Index from LogController" }
{ "time": "2016-02-22 01:12:16.3396", "level": "TRACE", "message": "Executed action Index from LogController" }
{ "time": "2016-02-22 01:18:00.9501", "level": "ERROR", "message": "A public action method 'dfg' was not found on controller 'ACTS.UI.Areas.Admin.Controllers.LogController'." }
{ "time": "2016-02-22 01:18:19.9331", "level": "TRACE", "message": "Start executing action test from AdminController" }
{ "time": "2016-02-22 01:18:19.9331", "level": "DEBUG", "message": "hello from Admin:TestAction" }
{ "time": "2016-02-22 01:18:19.9331", "level": "ERROR", "message": "test" }
{ "time": "2016-02-22 01:22:45.4190", "level": "TRACE", "message": "Start executing action Index from LogController" }
{ "time": "2016-02-22 01:22:45.4190", "level": "TRACE", "message": "Executed action Index from LogController" }
{ "time": "2016-02-22 01:23:25.5079", "level": "TRACE", "message": "Start executing action Index from LogController" }
{ "time": "2016-02-22 01:23:25.5079", "level": "TRACE", "message": "Executed action Index from LogController" }
{ "time": "2016-02-22 01:30:13.2246", "level": "TRACE", "message": "Start executing action Index from LogController" }
{ "time": "2016-02-22 01:30:13.2246", "level": "TRACE", "message": "Executed action Index from LogController" }
{ "time": "2016-02-22 01:31:17.9450", "level": "TRACE", "message": "Start executing action Index from LogController" }
{ "time": "2016-02-22 01:31:17.9450", "level": "TRACE", "message": "Executed action Index from LogController" }
{ "time": "2016-02-22 01:31:43.0080", "level": "TRACE", "message": "Start executing action Index from LogController" }
{ "time": "2016-02-22 01:31:43.0080", "level": "TRACE", "message": "Executed action Index from LogController" }
{ "time": "2016-02-22 01:32:04.3381", "level": "TRACE", "message": "Start executing action Index from LogController" }
{ "time": "2016-02-22 01:32:04.3381", "level": "TRACE", "message": "Executed action Index from LogController" }
{ "time": "2016-02-22 01:33:17.6802", "level": "TRACE", "message": "Start executing action Index from LogController" }
{ "time": "2016-02-22 01:33:17.6802", "level": "TRACE", "message": "Executed action Index from LogController" }
{ "time": "2016-02-22 01:35:31.7871", "level": "TRACE", "message": "Start executing action Index from LogController" }
{ "time": "2016-02-22 01:35:31.7871", "level": "TRACE", "message": "Executed action Index from LogController" }
{ "time": "2016-02-22 01:36:37.6878", "level": "TRACE", "message": "Start executing action Index from LogController" }
{ "time": "2016-02-22 01:36:37.6878", "level": "TRACE", "message": "Executed action Index from LogController" }
{ "time": "2016-02-22 01:50:28.9535", "level": "TRACE", "message": "Start executing action Index from LogController" }
{ "time": "2016-02-22 01:50:28.9535", "level": "TRACE", "message": "Executed action Index from LogController" }
{ "time": "2016-02-22 01:50:31.9668", "level": "ERROR", "message": "E:\\study\\ACTS\\ACTS.UI\\Areas\\Admin\\Views\\Log\\Logging.cshtml(67): error CS0117: 'GlobalRes' does not contain a definition for 'Details'" }
{ "time": "2016-02-22 01:54:01.5379", "level": "DEBUG", "message": "MVC Application initialized." }
{ "time": "2016-02-22 01:54:01.5741", "level": "TRACE", "message": "MVC Application start configuring." }
{ "time": "2016-02-22 01:54:02.9950", "level": "TRACE", "message": "MVC Application end configuring." }
{ "time": "2016-02-22 01:54:03.4552", "level": "TRACE", "message": "Owin start configuring." }
{ "time": "2016-02-22 01:54:03.4690", "level": "TRACE", "message": "Owin end configuring." }
{ "time": "2016-02-22 01:54:03.6802", "level": "TRACE", "message": "Start executing action Index from LogController" }
{ "time": "2016-02-22 01:54:05.4910", "level": "TRACE", "message": "Executed action Index from LogController" }
{ "time": "2016-02-22 01:54:37.9078", "level": "TRACE", "message": "Start executing action Index from LogController" }
{ "time": "2016-02-22 01:54:37.9078", "level": "TRACE", "message": "Executed action Index from LogController" }
{ "time": "2016-02-22 01:54:54.7657", "level": "TRACE", "message": "Start executing action Index from LogController" }
{ "time": "2016-02-22 01:54:54.7657", "level": "TRACE", "message": "Executed action Index from LogController" }
{ "time": "2016-02-22 01:55:32.8675", "level": "TRACE", "message": "Start executing action Index from LogController" }
{ "time": "2016-02-22 01:55:32.8675", "level": "TRACE", "message": "Executed action Index from LogController" }
{ "time": "2016-02-22 01:56:26.3045", "level": "TRACE", "message": "Start executing action Index from LogController" }
{ "time": "2016-02-22 01:56:26.3045", "level": "TRACE", "message": "Executed action Index from LogController" }
{ "time": "2016-02-22 01:57:33.5892", "level": "TRACE", "message": "Start executing action Index from LogController" }
{ "time": "2016-02-22 01:57:33.5892", "level": "TRACE", "message": "Executed action Index from LogController" }
{ "time": "2016-02-22 01:57:55.1759", "level": "TRACE", "message": "Start executing action Index from LogController" }
{ "time": "2016-02-22 01:57:55.1759", "level": "TRACE", "message": "Executed action Index from LogController" }
{ "time": "2016-02-22 01:58:54.2625", "level": "TRACE", "message": "Start executing action Index from LogController" }
{ "time": "2016-02-22 01:58:54.2625", "level": "TRACE", "message": "Executed action Index from LogController" }
{ "time": "2016-02-22 02:00:16.8352", "level": "TRACE", "message": "Start executing action Index from MyAccountController" }
{ "time": "2016-02-22 02:00:16.8652", "level": "TRACE", "message": "Executed action Index from MyAccountController" }
{ "time": "2016-02-22 02:03:04.8645", "level": "TRACE", "message": "Start executing action Index from LogController" }
{ "time": "2016-02-22 02:03:04.8645", "level": "TRACE", "message": "Executed action Index from LogController" }
{ "time": "2016-02-22 02:03:33.6891", "level": "TRACE", "message": "Start executing action Index from LogController" }
{ "time": "2016-02-22 02:03:33.6891", "level": "TRACE", "message": "Executed action Index from LogController" }
{ "time": "2016-02-22 02:03:49.0528", "level": "TRACE", "message": "Start executing action Index from LogController" }
{ "time": "2016-02-22 02:03:49.0528", "level": "TRACE", "message": "Executed action Index from LogController" }
{ "time": "2016-02-22 02:04:11.0162", "level": "TRACE", "message": "Start executing action Index from LogController" }
{ "time": "2016-02-22 02:04:11.0162", "level": "TRACE", "message": "Executed action Index from LogController" }
{ "time": "2016-02-22 02:05:17.5581", "level": "TRACE", "message": "Start executing action Index from LogController" }
{ "time": "2016-02-22 02:05:17.5581", "level": "TRACE", "message": "Executed action Index from LogController" }
{ "time": "2016-02-22 02:06:12.7423", "level": "TRACE", "message": "Start executing action Index from LogController" }
{ "time": "2016-02-22 02:06:12.7423", "level": "TRACE", "message": "Executed action Index from LogController" }
{ "time": "2016-02-22 02:11:20.5718", "level": "TRACE", "message": "Start executing action Index from LogController" }
{ "time": "2016-02-22 02:11:20.5718", "level": "TRACE", "message": "Executed action Index from LogController" }
{ "time": "2016-02-22 02:13:13.6149", "level": "DEBUG", "message": "MVC Application initialized." }
{ "time": "2016-02-22 02:13:13.6949", "level": "TRACE", "message": "MVC Application start configuring." }
{ "time": "2016-02-22 02:13:14.8953", "level": "TRACE", "message": "MVC Application end configuring." }
{ "time": "2016-02-22 02:13:15.4270", "level": "TRACE", "message": "Owin start configuring." }
{ "time": "2016-02-22 02:13:15.4510", "level": "TRACE", "message": "Owin end configuring." }
{ "time": "2016-02-22 02:13:15.6424", "level": "TRACE", "message": "Start executing action Index from LogController" }
{ "time": "2016-02-22 02:13:16.0288", "level": "TRACE", "message": "Executed action Index from LogController" }
{ "time": "2016-02-22 02:15:29.3057", "level": "TRACE", "message": "Start executing action Index from LogController" }
{ "time": "2016-02-22 02:15:29.3057", "level": "TRACE", "message": "Executed action Index from LogController" }
{ "time": "2016-02-22 02:18:08.1704", "level": "TRACE", "message": "Start executing action Index from LogController" }
{ "time": "2016-02-22 02:18:08.1704", "level": "TRACE", "message": "Executed action Index from LogController" }
{ "time": "2016-02-22 02:19:03.2307", "level": "TRACE", "message": "Start executing action Index from LogController" }
{ "time": "2016-02-22 02:19:03.2307", "level": "TRACE", "message": "Executed action Index from LogController" }
{ "time": "2016-02-22 02:23:19.2297", "level": "TRACE", "message": "Start executing action Index from HomeController" }
{ "time": "2016-02-22 02:23:26.4173", "level": "TRACE", "message": "Executed action Index from HomeController" }
{ "time": "2016-02-22 02:25:17.7166", "level": "TRACE", "message": "Start executing action AuthenticationLink from AccountController" }
{ "time": "2016-02-22 02:25:17.7256", "level": "TRACE", "message": "Executed action AuthenticationLink from AccountController" }
